ucache.py
ucache-0.1.5.dist-info/licenses/LICENSE
ucache-0.1.5.dist-info/METADATA
ucache-0.1.5.dist-info/WHEEL
ucache-0.1.5.dist-info/top_level.txt
ucache-0.1.5.dist-info/RECORD
