Metadata-Version: 2.4
Name: ucache
Version: 0.1.5
Summary: lightweight and efficient caching library
Author-email: Charles Leifer <coleifer@gmail.com>
Project-URL: Repository, https://github.com/coleifer/ucache
Project-URL: Documentation, https://github.com/coleifer/ucache/blob/master/README.md
Classifier: Programming Language :: Python :: 2
Classifier: Programming Language :: Python :: 3
Classifier: Topic :: Software Development :: Libraries :: Python Modules
License-File: LICENSE
Provides-Extra: pylibmc
Requires-Dist: pylibmc; extra == "pylibmc"
Provides-Extra: memcached
Requires-Dist: pymemcached; extra == "memcached"
Provides-Extra: redis
Requires-Dist: redis; extra == "redis"
Provides-Extra: sqlite
Requires-Dist: peewee; extra == "sqlite"
Provides-Extra: greendb
Requires-Dist: greendb; extra == "greendb"
Dynamic: license-file
